matc/__init__.py
matc/constants.py
matc/globa.py
matc/main.py
matc/main_object.py
matc/matc.qss
matc/matc_rc.py
matc/settings.py
matc/gui/__init__.py
matc/gui/breathing_dlg.py
matc/gui/intro_dlg.py
matc/gui/reusable_components.py
matc/gui/settings_win.py
matc/res/com.matc.mindfulness-at-the-computer.plist
matc/res/matc.qrc
matc/res/audio/big_bell[cc0]_fade_out.wav
matc/res/audio/small_bell_short[cc0].wav
matc/res/icons/checkbox_checked.svg
matc/res/icons/checkbox_unchecked.svg
matc/res/icons/down.svg
matc/res/icons/down_disabled.svg
matc/res/icons/icon-b.png
matc/res/icons/icon-br.png
matc/res/icons/icon-r.png
matc/res/icons/icon-suspend.png
matc/res/icons/icon.icns
matc/res/icons/icon.ico
matc/res/icons/icon.png
matc/res/icons/icon.xcf
matc/res/icons/matc_draw_io_icons.drawio
matc/res/icons/moving-icon-gradient.svg
matc/res/icons/svg-rotate-and-export.py
matc/res/icons/up.svg
matc/res/icons/up_disabled.svg
matc/res/icons/open_iconic/ICON-LICENSE
matc/res/icons/open_iconic/arrow-bottom-2x.png
matc/res/icons/open_iconic/arrow-bottom-3x.png
matc/res/icons/open_iconic/arrow-bottom-4x.png
matc/res/icons/open_iconic/arrow-bottom-6x.png
matc/res/icons/open_iconic/arrow-bottom-8x.png
matc/res/icons/open_iconic/arrow-bottom.png
matc/res/icons/open_iconic/arrow-circle-bottom-2x.png
matc/res/icons/open_iconic/arrow-circle-bottom-3x.png
matc/res/icons/open_iconic/arrow-circle-bottom-4x.png
matc/res/icons/open_iconic/arrow-circle-bottom-6x.png
matc/res/icons/open_iconic/arrow-circle-bottom-8x.png
matc/res/icons/open_iconic/arrow-circle-bottom.png
matc/res/icons/open_iconic/arrow-circle-top-2x.png
matc/res/icons/open_iconic/arrow-circle-top-3x.png
matc/res/icons/open_iconic/arrow-circle-top-4x.png
matc/res/icons/open_iconic/arrow-circle-top-6x.png
matc/res/icons/open_iconic/arrow-circle-top-8x.png
matc/res/icons/open_iconic/arrow-circle-top.png
matc/res/icons/open_iconic/arrow-thick-bottom-2x.png
matc/res/icons/open_iconic/arrow-thick-bottom-3x.png
mindfulness_at_the_computer-1.0.0a10.dist-info/LICENSE.txt
mindfulness_at_the_computer-1.0.0a10.dist-info/METADATA
mindfulness_at_the_computer-1.0.0a10.dist-info/WHEEL
mindfulness_at_the_computer-1.0.0a10.dist-info/entry_points.txt
mindfulness_at_the_computer-1.0.0a10.dist-info/top_level.txt
mindfulness_at_the_computer-1.0.0a10.dist-info/RECORD
