Metadata-Version: 2.1
Name: mindfulness-at-the-computer
Version: 1.0.0a10
Summary: Helps you stay mindful of your breathing while using your computer.
Home-page: https://mindfulness-at-the-computer.gitlab.io
Author: Tord Dellsén, and others
Author-email: tord.dellsen@gmail.com
License: GPLv3
Platform: UNKNOWN
Classifier: License :: OSI Approved :: GNU General Public License v3 (GPLv3)
Classifier: Programming Language :: Python
Classifier: Programming Language :: Python :: 3
Classifier: Development Status :: 3 - Alpha
Classifier: Intended Audience :: End Users/Desktop
Classifier: Topic :: Other/Nonlisted Topic
Requires-Python: >=3.6.0
License-File: LICENSE.txt
Requires-Dist: PySide6 (>=6.2)
